tokenlists/__init__.py
tokenlists/_cli.py
tokenlists/config.py
tokenlists/manager.py
tokenlists/py.typed
tokenlists/typing.py
tokenlists/version.py
tokenlists-0.1.7.dist-info/LICENSE
tokenlists-0.1.7.dist-info/METADATA
tokenlists-0.1.7.dist-info/WHEEL
tokenlists-0.1.7.dist-info/entry_points.txt
tokenlists-0.1.7.dist-info/top_level.txt
tokenlists-0.1.7.dist-info/RECORD
