Metadata-Version: 2.1
Name: tokenlists
Version: 0.1.7
Summary: Python implementation of Uniswaps' tokenlists
Home-page: https://github.com/ApeWorX/py-tokenlists
Author: Ben Hauser
Author-email: ben@hauser.id
License: Apache-2.0
Keywords: ethereum
Classifier: Development Status :: 5 - Production/Stable
Classifier: Intended Audience :: Developers
Classifier: License :: OSI Approved :: Apache Software License
Classifier: Natural Language :: English
Classifier: Operating System :: MacOS
Classifier: Operating System :: POSIX
Classifier: Programming Language :: Python :: 3
Classifier: Programming Language :: Python :: 3.8
Classifier: Programming Language :: Python :: 3.9
Classifier: Programming Language :: Python :: 3.10
Classifier: Programming Language :: Python :: 3.11
Requires-Python: >=3.8,<4
Provides-Extra: test
Provides-Extra: lint
Provides-Extra: doc
Provides-Extra: release
Provides-Extra: dev
License-File: LICENSE
